{
    "monthlyPackages": {
        "tenMembers": "a[title='Starter']",
        "upToFifty": "a[title='Standard']",
        "upToHundred": "a[title='Growth']"
    },
    "otherPackageRelated": {
        "enterprise": ".vsp-c-pricing-plan-list--annual > :nth-child(4) > #getAQuote",
        "switchToMonthly": ".vsp-c-switch-pricing-plan-list > :nth-child(1)",
        "swithchToAnually": ".checked",
        "cookies": "#cookieGotIt"
    },
    "registration": {
        "email": "input[name='email']",
        "password": "input[type='password']",
        "noOfUsers": "input[name='number_of_users']",
        "checkBox": "input[type='checkbox']",
        "seePass": "button[type='button']",
        "submit": "button[type='submit']",
        "registerWithGoogle": "button[class='vs-c-btn vs-c-btn--social-auth vs-c-btn--gp']",
        "registerWithFacebook": "button[class='vs-c-btn vs-c-btn--social-auth vs-c-btn--fb']",
        "registerWithTwitter": "button[class='vs-c-btn vs-c-btn--social-auth vs-c-btn--tw']",
        "registerWithRegzenLOL": "button[class='vs-c-btn vs-c-btn--social-auth vs-c-btn--regzen']",
        "goToLogin": "a[href='/login']"
    },
    "errors":{
        "email":"div[class='el-form-item']:first-child span",
        "password":"div[class='el-form-item']:nth-child(2) span",
        "noOfUsers":"div[class='el-form-item']:nth-child(3) span",
        "checkBox":"div[class='el-form-item']:nth-child(4) span[class='el-form-item__error el-form-item-error--top']",
        "beckend":".el-message__group > p",
        "all": "div[class=vs-c-form-item__error-wrapper]"
    },

    "acceptCookies":"a#cookieGotIt",
    "titlePricingPlans": ".vsp-c-grid > :nth-child(1) > .vsp-c-section-title",
    "closeMeet":".vsp-c-grid > :nth-child(1) > .vsp-c-section-title"
}
